leaf_airflow_operator/__init__.py
leaf_airflow_operator/hooks/__init__.py
leaf_airflow_operator/hooks/leaf_hook.py
leaf_airflow_operator/operators/__init__.py
leaf_airflow_operator/operators/leaf_operator.py
leaf_airflow_operator/sensors/__init__.py
leaf_airflow_operator/sensors/leaf_sensor.py
leaf_airflow_operator-0.1.5.dist-info/licenses/LICENSE
leaf_airflow_operator-0.1.5.dist-info/METADATA
leaf_airflow_operator-0.1.5.dist-info/WHEEL
leaf_airflow_operator-0.1.5.dist-info/top_level.txt
leaf_airflow_operator-0.1.5.dist-info/RECORD
