Metadata-Version: 2.4
Name: leaf-airflow-operator
Version: 0.1.5
Summary: Custom Apache Airflow operator to interact with Leaf Agriculture API
Author: Luiz Henrique Zambom Santana
Classifier: Programming Language :: Python :: 3
Classifier: License :: OSI Approved :: MIT License
License-File: LICENSE
Requires-Dist: apache-airflow>=2.4.0
Requires-Dist: requests>=2.25.0
Dynamic: author
Dynamic: classifier
Dynamic: license-file
Dynamic: requires-dist
Dynamic: summary
